{"kitManifest":{"$":{"name":"SysMikPlatScc52x","checksum":"7955ba73","hasNatives":"true","doc":"false","version":"1.2.28","vendor":"SysMik","description":"Platform support for Scc-52x devices","buildHost":"gs-xp-7-001","buildTime":"2013-09-10T17:00:18.562+02:00"},"depends":[{"depend":[{"$":{"on":"sys 1.2"}}]}],"type":[{"$":{"id":"0","name":"IoAI","sizeof":"48","base":"sys::Component"},"facets":[{"str":[{"$":{"name":"niagaraIcon","val":"module://icons/x16/control/numericPoint.png"}}]}],"slot":[{"$":{"id":"0","name":"channel","type":"int","flags":"c","default":"0"},"facets":[{"int":[{"$":{"name":"min","val":"0"}},{"$":{"name":"max","val":"4"}}],"bool":[{"$":{"name":"config","val":"true"}}],"str":[{"$":{"name":"range","val":"UI1, UI2, UI3, UI4, UI5"}}]}]},{"$":{"id":"1","name":"sensorType","type":"int","flags":"c","default":"0"},"facets":[{"int":[{"$":{"name":"min","val":"0"}},{"$":{"name":"max","val":"9"}}],"bool":[{"$":{"name":"config","val":"true"}}],"str":[{"$":{"name":"range","val":"voltage_0_10V, current_0_20mA, current_4_20mA, resistance_1500Ohm, resistance_10kOhm, resistance_300kOhm, temperature_Ni1000, temperature_Pt1000, temperature_Pt100, temperature_LG_NI_1000"}}]}]},{"$":{"id":"2","name":"out","type":"float","default":"0.0"},"facets":[{"bool":[{"$":{"name":"readonly","val":"true"}}]}]}]},{"$":{"id":"1","name":"IoAO","sizeof":"44","base":"sys::Component"},"facets":[{"str":[{"$":{"name":"niagaraIcon","val":"module://icons/x16/control/numericPointWr.png"}}]}],"slot":[{"$":{"id":"0","name":"channel","type":"byte","flags":"c","default":"0"},"facets":[{"int":[{"$":{"name":"min","val":"0"}},{"$":{"name":"max","val":"3"}}],"bool":[{"$":{"name":"config","val":"true"}}],"str":[{"$":{"name":"range","val":"AO1, AO2, AO3, AO4"}}]}]},{"$":{"id":"1","name":"in","type":"float","default":"0.0"},"facets":[{"float":[{"$":{"name":"min","val":"0.0"}},{"$":{"name":"max","val":"10.0"}}],"str":[{"$":{"name":"unit","val":"volt"}}]}]}]},{"$":{"id":"2","name":"IoCount","sizeof":"44","base":"sys::Component"},"facets":[{"str":[{"$":{"name":"niagaraIcon","val":"module://icons/x16/control/enumPoint.png"}}]}],"slot":[{"$":{"id":"0","name":"channel","type":"byte","flags":"c","default":"0"},"facets":[{"int":[{"$":{"name":"min","val":"0"}},{"$":{"name":"max","val":"4"}}],"bool":[{"$":{"name":"config","val":"true"}}],"str":[{"$":{"name":"range","val":"UI1, UI2, UI3, UI4, UI5"}}]}]},{"$":{"id":"1","name":"out","type":"int","default":"0"},"facets":[{"bool":[{"$":{"name":"readonly","val":"true"}}]}]},{"$":{"id":"2","name":"Reset","type":"int","flags":"a"}}]},{"$":{"id":"3","name":"IoDI","sizeof":"40","base":"sys::Component"},"facets":[{"str":[{"$":{"name":"niagaraIcon","val":"module://icons/x16/control/booleanPoint.png"}}]}],"slot":[{"$":{"id":"0","name":"channel","type":"byte","flags":"c","default":"0"},"facets":[{"int":[{"$":{"name":"min","val":"0"}},{"$":{"name":"max","val":"4"}}],"bool":[{"$":{"name":"config","val":"true"}}],"str":[{"$":{"name":"range","val":"UI1, UI2, UI3, UI4, UI5"}}]}]},{"$":{"id":"1","name":"sensorType","type":"byte","flags":"c","default":"0"},"facets":[{"int":[{"$":{"name":"min","val":"0"}},{"$":{"name":"max","val":"3"}}],"bool":[{"$":{"name":"config","val":"true"}}],"str":[{"$":{"name":"range","val":"binary, binary_inverted, contact, contact_inverted"}}]}]},{"$":{"id":"2","name":"out","type":"bool"},"facets":[{"bool":[{"$":{"name":"readonly","val":"true"}}]}]}]},{"$":{"id":"4","name":"IoDO","sizeof":"40","base":"sys::Component"},"facets":[{"str":[{"$":{"name":"niagaraIcon","val":"module://icons/x16/control/booleanPointWr.png"}}]}],"slot":[{"$":{"id":"0","name":"channel","type":"byte","flags":"c","default":"0"},"facets":[{"int":[{"$":{"name":"min","val":"0"}},{"$":{"name":"max","val":"6"}}],"bool":[{"$":{"name":"config","val":"true"}}],"str":[{"$":{"name":"range","val":"Triac1, Triac2, Rel3, Rel4, Rel5, Triac6, Triac7"}}]}]},{"$":{"id":"1","name":"in","type":"bool","default":"false"}}]},{"$":{"id":"5","name":"ManLed","sizeof":"40","base":"sys::Component"},"facets":[{"str":[{"$":{"name":"niagaraIcon","val":"module://icons/x16/control/booleanPointWr.png"}}]}],"slot":[{"$":{"id":"0","name":"channel","type":"byte","flags":"c","default":"0"},"facets":[{"int":[{"$":{"name":"min","val":"0"}},{"$":{"name":"max","val":"2"}}],"bool":[{"$":{"name":"config","val":"true"}}],"str":[{"$":{"name":"range","val":"Led1_yellow, Led2_green, Led3_red"}}]}]},{"$":{"id":"1","name":"in","type":"bool","default":"false"}}]},{"$":{"id":"6","name":"ManRotarySwitch","sizeof":"44","base":"sys::Component"},"facets":[{"str":[{"$":{"name":"niagaraIcon","val":"module://icons/x16/control/numericPoint.png"}}]}],"slot":[{"$":{"id":"0","name":"channel","type":"byte","flags":"c","default":"0"},"facets":[{"int":[{"$":{"name":"min","val":"0"}},{"$":{"name":"max","val":"1"}}],"bool":[{"$":{"name":"config","val":"true"}}],"str":[{"$":{"name":"range","val":"SW_1, SW_2"}}]}]},{"$":{"id":"1","name":"out","type":"int"},"facets":[{"bool":[{"$":{"name":"readonly","val":"true"}}]}]}]},{"$":{"id":"7","name":"MpAddressing","sizeof":"44","base":"sys::Component"},"facets":[{"str":[{"$":{"name":"niagaraIcon","val":"module://icons/x16/control/numericPointWr.png"}}]}],"slot":[{"$":{"id":"0","name":"address","type":"byte","flags":"c","default":"0"},"facets":[{"int":[{"$":{"name":"min","val":"0"}},{"$":{"name":"max","val":"7"}}],"bool":[{"$":{"name":"config","val":"true"}}],"str":[{"$":{"name":"range","val":"MP_1, MP_2, MP_3, MP_4, MP_5, MP_6, MP_7, MP_8"}}]}]},{"$":{"id":"1","name":"deviceCategory","type":"byte"},"facets":[{"int":[{"$":{"name":"min","val":"0"}},{"$":{"name":"max","val":"15"}}],"str":[{"$":{"name":"range","val":"Spare, Universal_IO, Air, Valve_linear, Valve_rotary, Window_Ventilation, Fire_Smoke, Sensor, VAV, MPL, xA, xB, xC, xD, xE, third_Party"}}],"bool":[{"$":{"name":"readonly","val":"true"}}]}]},{"$":{"id":"2","name":"builtInModule","type":"int"},"facets":[{"int":[{"$":{"name":"min","val":"0"}},{"$":{"name":"max","val":"15"}}],"str":[{"$":{"name":"range","val":"None, SR_95, Phase_Cut, Y, Temperature, LON, mA, BAE_2, LEN, Hartann, Ohm_135, CAN, EPIV, xD, xE, third_Party"}}],"bool":[{"$":{"name":"readonly","val":"true"}}]}]},{"$":{"id":"3","name":"deviceFamily","type":"short"},"facets":[{"int":[{"$":{"name":"min","val":"0"}},{"$":{"name":"max","val":"255"}}],"bool":[{"$":{"name":"readonly","val":"true"}}]}]},{"$":{"id":"4","name":"SetMpAddressToPpAddress","type":"void","flags":"a"}},{"$":{"id":"5","name":"GetSeriesNumberAtPp","type":"void","flags":"a"}},{"$":{"id":"6","name":"SetAddressAtMpBroadcast","type":"void","flags":"a"}},{"$":{"id":"7","name":"GetSeriesNumberAtMpAdrress","type":"void","flags":"a"}}]},{"$":{"id":"8","name":"MpBus","sizeof":"100","base":"sys::Component"},"facets":[{"str":[{"$":{"name":"niagaraIcon","val":"module://icons/x16/control/numericPointWr.png"}}]}],"slot":[{"$":{"id":"0","name":"MpAddr1","type":"bool"},"facets":[{"bool":[{"$":{"name":"readonly","val":"true"}}]}]},{"$":{"id":"1","name":"deviceCategory1","type":"byte"},"facets":[{"int":[{"$":{"name":"min","val":"0"}},{"$":{"name":"max","val":"15"}}],"str":[{"$":{"name":"range","val":"Spare, Universal_IO, Air, Valve_linear, Valve_rotary, Window_Ventilation, Fire_Smoke, Sensor, VAV, MPL, xA, xB, xC, xD, xE, third_Party"}}],"bool":[{"$":{"name":"readonly","val":"true"}}]}]},{"$":{"id":"2","name":"builtInModule1","type":"int"},"facets":[{"int":[{"$":{"name":"min","val":"0"}},{"$":{"name":"max","val":"15"}}],"str":[{"$":{"name":"range","val":"None, SR_95, Phase_Cut, Y, Temperature, LON, mA, BAE_2, LEN, Hartann, Ohm_135, CAN, EPIV, xD, xE, third_Party"}}],"bool":[{"$":{"name":"readonly","val":"true"}}]}]},{"$":{"id":"3","name":"deviceFamily1","type":"short"},"facets":[{"int":[{"$":{"name":"min","val":"0"}},{"$":{"name":"max","val":"255"}}],"bool":[{"$":{"name":"readonly","val":"true"}}]}]},{"$":{"id":"4","name":"MpAddr2","type":"bool"},"facets":[{"bool":[{"$":{"name":"readonly","val":"true"}}]}]},{"$":{"id":"5","name":"deviceCategory2","type":"byte"},"facets":[{"int":[{"$":{"name":"min","val":"0"}},{"$":{"name":"max","val":"15"}}],"str":[{"$":{"name":"range","val":"Spare, Universal_IO, Air, Valve_linear, Valve_rotary, Window_Ventilation, Fire_Smoke, Sensor, VAV, MPL, xA, xB, xC, xD, xE, third_Party"}}],"bool":[{"$":{"name":"readonly","val":"true"}}]}]},{"$":{"id":"6","name":"builtInModule2","type":"int"},"facets":[{"int":[{"$":{"name":"min","val":"0"}},{"$":{"name":"max","val":"15"}}],"str":[{"$":{"name":"range","val":"None, SR_95, Phase_Cut, Y, Temperature, LON, mA, BAE_2, LEN, Hartann, Ohm_135, CAN, EPIV, xD, xE, third_Party"}}],"bool":[{"$":{"name":"readonly","val":"true"}}]}]},{"$":{"id":"7","name":"deviceFamily2","type":"short"},"facets":[{"int":[{"$":{"name":"min","val":"0"}},{"$":{"name":"max","val":"255"}}],"bool":[{"$":{"name":"readonly","val":"true"}}]}]},{"$":{"id":"8","name":"MpAddr3","type":"bool"},"facets":[{"bool":[{"$":{"name":"readonly","val":"true"}}]}]},{"$":{"id":"9","name":"deviceCategory3","type":"byte"},"facets":[{"int":[{"$":{"name":"min","val":"0"}},{"$":{"name":"max","val":"15"}}],"str":[{"$":{"name":"range","val":"Spare, Universal_IO, Air, Valve_linear, Valve_rotary, Window_Ventilation, Fire_Smoke, Sensor, VAV, MPL, xA, xB, xC, xD, xE, third_Party"}}],"bool":[{"$":{"name":"readonly","val":"true"}}]}]},{"$":{"id":"10","name":"builtInModule3","type":"int"},"facets":[{"int":[{"$":{"name":"min","val":"0"}},{"$":{"name":"max","val":"15"}}],"str":[{"$":{"name":"range","val":"None, SR_95, Phase_Cut, Y, Temperature, LON, mA, BAE_2, LEN, Hartann, Ohm_135, CAN, EPIV, xD, xE, third_Party"}}],"bool":[{"$":{"name":"readonly","val":"true"}}]}]},{"$":{"id":"11","name":"deviceFamily3","type":"short"},"facets":[{"int":[{"$":{"name":"min","val":"0"}},{"$":{"name":"max","val":"255"}}],"bool":[{"$":{"name":"readonly","val":"true"}}]}]},{"$":{"id":"12","name":"MpAddr4","type":"bool"},"facets":[{"bool":[{"$":{"name":"readonly","val":"true"}}]}]},{"$":{"id":"13","name":"deviceCategory4","type":"byte"},"facets":[{"int":[{"$":{"name":"min","val":"0"}},{"$":{"name":"max","val":"15"}}],"str":[{"$":{"name":"range","val":"Spare, Universal_IO, Air, Valve_linear, Valve_rotary, Window_Ventilation, Fire_Smoke, Sensor, VAV, MPL, xA, xB, xC, xD, xE, third_Party"}}],"bool":[{"$":{"name":"readonly","val":"true"}}]}]},{"$":{"id":"14","name":"builtInModule4","type":"int"},"facets":[{"int":[{"$":{"name":"min","val":"0"}},{"$":{"name":"max","val":"15"}}],"str":[{"$":{"name":"range","val":"None, SR_95, Phase_Cut, Y, Temperature, LON, mA, BAE_2, LEN, Hartann, Ohm_135, CAN, EPIV, xD, xE, third_Party"}}],"bool":[{"$":{"name":"readonly","val":"true"}}]}]},{"$":{"id":"15","name":"deviceFamily4","type":"short"},"facets":[{"int":[{"$":{"name":"min","val":"0"}},{"$":{"name":"max","val":"255"}}],"bool":[{"$":{"name":"readonly","val":"true"}}]}]},{"$":{"id":"16","name":"MpAddr5","type":"bool"},"facets":[{"bool":[{"$":{"name":"readonly","val":"true"}}]}]},{"$":{"id":"17","name":"deviceCategory5","type":"byte"},"facets":[{"int":[{"$":{"name":"min","val":"0"}},{"$":{"name":"max","val":"15"}}],"str":[{"$":{"name":"range","val":"Spare, Universal_IO, Air, Valve_linear, Valve_rotary, Window_Ventilation, Fire_Smoke, Sensor, VAV, MPL, xA, xB, xC, xD, xE, third_Party"}}],"bool":[{"$":{"name":"readonly","val":"true"}}]}]},{"$":{"id":"18","name":"builtInModule5","type":"int"},"facets":[{"int":[{"$":{"name":"min","val":"0"}},{"$":{"name":"max","val":"15"}}],"str":[{"$":{"name":"range","val":"None, SR_95, Phase_Cut, Y, Temperature, LON, mA, BAE_2, LEN, Hartann, Ohm_135, CAN, EPIV, xD, xE, third_Party"}}],"bool":[{"$":{"name":"readonly","val":"true"}}]}]},{"$":{"id":"19","name":"deviceFamily5","type":"short"},"facets":[{"int":[{"$":{"name":"min","val":"0"}},{"$":{"name":"max","val":"255"}}],"bool":[{"$":{"name":"readonly","val":"true"}}]}]},{"$":{"id":"20","name":"MpAddr6","type":"bool"},"facets":[{"bool":[{"$":{"name":"readonly","val":"true"}}]}]},{"$":{"id":"21","name":"deviceCategory6","type":"byte"},"facets":[{"int":[{"$":{"name":"min","val":"0"}},{"$":{"name":"max","val":"15"}}],"str":[{"$":{"name":"range","val":"Spare, Universal_IO, Air, Valve_linear, Valve_rotary, Window_Ventilation, Fire_Smoke, Sensor, VAV, MPL, xA, xB, xC, xD, xE, third_Party"}}],"bool":[{"$":{"name":"readonly","val":"true"}}]}]},{"$":{"id":"22","name":"builtInModule6","type":"int"},"facets":[{"int":[{"$":{"name":"min","val":"0"}},{"$":{"name":"max","val":"15"}}],"str":[{"$":{"name":"range","val":"None, SR_95, Phase_Cut, Y, Temperature, LON, mA, BAE_2, LEN, Hartann, Ohm_135, CAN, EPIV, xD, xE, third_Party"}}],"bool":[{"$":{"name":"readonly","val":"true"}}]}]},{"$":{"id":"23","name":"deviceFamily6","type":"short"},"facets":[{"int":[{"$":{"name":"min","val":"0"}},{"$":{"name":"max","val":"255"}}],"bool":[{"$":{"name":"readonly","val":"true"}}]}]},{"$":{"id":"24","name":"MpAddr7","type":"bool"},"facets":[{"bool":[{"$":{"name":"readonly","val":"true"}}]}]},{"$":{"id":"25","name":"deviceCategory7","type":"byte"},"facets":[{"int":[{"$":{"name":"min","val":"0"}},{"$":{"name":"max","val":"15"}}],"str":[{"$":{"name":"range","val":"Spare, Universal_IO, Air, Valve_linear, Valve_rotary, Window_Ventilation, Fire_Smoke, Sensor, VAV, MPL, xA, xB, xC, xD, xE, third_Party"}}],"bool":[{"$":{"name":"readonly","val":"true"}}]}]},{"$":{"id":"26","name":"builtInModule7","type":"int"},"facets":[{"int":[{"$":{"name":"min","val":"0"}},{"$":{"name":"max","val":"15"}}],"str":[{"$":{"name":"range","val":"None, SR_95, Phase_Cut, Y, Temperature, LON, mA, BAE_2, LEN, Hartann, Ohm_135, CAN, EPIV, xD, xE, third_Party"}}],"bool":[{"$":{"name":"readonly","val":"true"}}]}]},{"$":{"id":"27","name":"deviceFamily7","type":"short"},"facets":[{"int":[{"$":{"name":"min","val":"0"}},{"$":{"name":"max","val":"255"}}],"bool":[{"$":{"name":"readonly","val":"true"}}]}]},{"$":{"id":"28","name":"MpAddr8","type":"bool"},"facets":[{"bool":[{"$":{"name":"readonly","val":"true"}}]}]},{"$":{"id":"29","name":"deviceCategory8","type":"byte"},"facets":[{"int":[{"$":{"name":"min","val":"0"}},{"$":{"name":"max","val":"15"}}],"str":[{"$":{"name":"range","val":"Spare, Universal_IO, Air, Valve_linear, Valve_rotary, Window_Ventilation, Fire_Smoke, Sensor, VAV, MPL, xA, xB, xC, xD, xE, third_Party"}}],"bool":[{"$":{"name":"readonly","val":"true"}}]}]},{"$":{"id":"30","name":"builtInModule8","type":"int"},"facets":[{"int":[{"$":{"name":"min","val":"0"}},{"$":{"name":"max","val":"15"}}],"str":[{"$":{"name":"range","val":"None, SR_95, Phase_Cut, Y, Temperature, LON, mA, BAE_2, LEN, Hartann, Ohm_135, CAN, EPIV, xD, xE, third_Party"}}],"bool":[{"$":{"name":"readonly","val":"true"}}]}]},{"$":{"id":"31","name":"deviceFamily8","type":"short"},"facets":[{"int":[{"$":{"name":"min","val":"0"}},{"$":{"name":"max","val":"255"}}],"bool":[{"$":{"name":"readonly","val":"true"}}]}]}]},{"$":{"id":"9","name":"MpDamper","sizeof":"72","base":"sys::Component"},"facets":[{"str":[{"$":{"name":"niagaraIcon","val":"module://icons/x16/control/numericPointWr.png"}}]}],"slot":[{"$":{"id":"0","name":"address","type":"byte","flags":"c","default":"0"},"facets":[{"int":[{"$":{"name":"min","val":"0"}},{"$":{"name":"max","val":"7"}}],"bool":[{"$":{"name":"config","val":"true"}}],"str":[{"$":{"name":"range","val":"MP_1, MP_2, MP_3, MP_4, MP_5, MP_6, MP_7, MP_8"}}]}]},{"$":{"id":"1","name":"in","type":"float"},"facets":[{"float":[{"$":{"name":"min","val":"0.0"}},{"$":{"name":"max","val":"1.0"}}],"int":[{"$":{"name":"precision","val":"3"}}]}]},{"$":{"id":"2","name":"ySensorType","type":"byte","flags":"c","default":"0"},"facets":[{"int":[{"$":{"name":"min","val":"0"}},{"$":{"name":"max","val":"2"}}],"bool":[{"$":{"name":"config","val":"true"}}],"str":[{"$":{"name":"range","val":"voltage, passive850_1600, passive200_50000, switch"}}]}]},{"$":{"id":"3","name":"outVoltage","type":"float"},"facets":[{"str":[{"$":{"name":"unit","val":"volt"}}],"bool":[{"$":{"name":"readonly","val":"true"}}]}]},{"$":{"id":"4","name":"outResistance","type":"float"},"facets":[{"str":[{"$":{"name":"unit","val":"ohm"}}],"bool":[{"$":{"name":"readonly","val":"true"}}]}]},{"$":{"id":"5","name":"outSetPointFeedback","type":"float"},"facets":[{"int":[{"$":{"name":"precision","val":"3"}}],"bool":[{"$":{"name":"readonly","val":"true"}}]}]},{"$":{"id":"6","name":"outActualPos","type":"float"},"facets":[{"int":[{"$":{"name":"precision","val":"3"}}],"bool":[{"$":{"name":"readonly","val":"true"}}]}]},{"$":{"id":"7","name":"heavyUsage","type":"bool"},"facets":[{"bool":[{"$":{"name":"readonly","val":"true"}}]}]},{"$":{"id":"8","name":"controlRangeExtended","type":"bool"},"facets":[{"bool":[{"$":{"name":"readonly","val":"true"}}]}]},{"$":{"id":"9","name":"overload","type":"bool"},"facets":[{"bool":[{"$":{"name":"readonly","val":"true"}}]}]},{"$":{"id":"10","name":"setForcedControl","type":"byte","flags":"c","default":"1"},"facets":[{"int":[{"$":{"name":"min","val":"1"}},{"$":{"name":"max","val":"10"}}],"bool":[{"$":{"name":"config","val":"true"}}],"str":[{"$":{"name":"range","val":"Open, Close, Max, Min, Mid, Stop, Percent100, Fast_close, Fast_open, Stop_10s"}}]}]},{"$":{"id":"11","name":"deviceCategory","type":"byte"},"facets":[{"int":[{"$":{"name":"min","val":"0"}},{"$":{"name":"max","val":"15"}}],"str":[{"$":{"name":"range","val":"Spare, Universal_IO, Air, Valve_linear, Valve_rotary, Window_Ventilation, Fire_Smoke, Sensor, VAV, MPL, xA, xB, xC, xD, xE, third_Party"}}],"bool":[{"$":{"name":"readonly","val":"true"}}]}]},{"$":{"id":"12","name":"builtInModule","type":"int"},"facets":[{"int":[{"$":{"name":"min","val":"0"}},{"$":{"name":"max","val":"15"}}],"str":[{"$":{"name":"range","val":"None, SR_95, Phase_Cut, Y, Temperature, LON, mA, BAE_2, LEN, Hartann, Ohm_135, CAN, EPIV, xD, xE, third_Party"}}],"bool":[{"$":{"name":"readonly","val":"true"}}]}]},{"$":{"id":"13","name":"deviceFamily","type":"short"},"facets":[{"int":[{"$":{"name":"min","val":"0"}},{"$":{"name":"max","val":"255"}}],"bool":[{"$":{"name":"readonly","val":"true"}}]}]},{"$":{"id":"14","name":"Set_Forced_Control","type":"void","flags":"a"}}]},{"$":{"id":"10","name":"MpDataPool","sizeof":"48","base":"sys::Component"},"facets":[{"str":[{"$":{"name":"niagaraIcon","val":"module://icons/x16/control/numericPointWr.png"}}]}],"slot":[{"$":{"id":"0","name":"address","type":"byte","flags":"c","default":"0"},"facets":[{"int":[{"$":{"name":"min","val":"0"}},{"$":{"name":"max","val":"7"}}],"bool":[{"$":{"name":"config","val":"true"}}],"str":[{"$":{"name":"range","val":"MP_1, MP_2, MP_3, MP_4, MP_5, MP_6, MP_7, MP_8"}}]}]},{"$":{"id":"1","name":"iD","type":"byte","flags":"c","default":"0"},"facets":[{"int":[{"$":{"name":"min","val":"0"}},{"$":{"name":"max","val":"127"}}],"bool":[{"$":{"name":"config","val":"true"}}]}]},{"$":{"id":"2","name":"outData","type":"int"},"facets":[{"bool":[{"$":{"name":"readonly","val":"true"}}]}]},{"$":{"id":"3","name":"profileType","type":"byte"},"facets":[{"bool":[{"$":{"name":"readonly","val":"true"}}]}]},{"$":{"id":"4","name":"profileCategory","type":"short"},"facets":[{"int":[{"$":{"name":"min","val":"0"}},{"$":{"name":"max","val":"255"}}],"str":[{"$":{"name":"range","val":"Spare_0, Actuator, Humidity, Light, Occupancy, Pressure, Air_Flow, Air_Quality, Temperature, Temp_Hum_Air_Quality, Temp_Hum_Air_Pressure, Room_Terminal, Analoge_Input, Digital_Input, Analog_Output, Digital_Output, Mixed_Input, Mixed_Output, Combined_IO, Pump_Fan"}}],"bool":[{"$":{"name":"readonly","val":"true"}}]}]}]},{"$":{"id":"11","name":"MpFireSmokeDamper","sizeof":"60","base":"sys::Component"},"facets":[{"str":[{"$":{"name":"niagaraIcon","val":"module://icons/x16/control/numericPointWr.png"}}]}],"slot":[{"$":{"id":"0","name":"address","type":"byte","flags":"c","default":"0"},"facets":[{"int":[{"$":{"name":"min","val":"0"}},{"$":{"name":"max","val":"7"}}],"bool":[{"$":{"name":"config","val":"true"}}],"str":[{"$":{"name":"range","val":"MP_1, MP_2, MP_3, MP_4, MP_5, MP_6, MP_7, MP_8"}}]}]},{"$":{"id":"1","name":"heavyUsage","type":"bool"},"facets":[{"bool":[{"$":{"name":"readonly","val":"true"}}]}]},{"$":{"id":"2","name":"controlRangeExtended","type":"bool"},"facets":[{"bool":[{"$":{"name":"readonly","val":"true"}}]}]},{"$":{"id":"3","name":"overload","type":"bool"},"facets":[{"bool":[{"$":{"name":"readonly","val":"true"}}]}]},{"$":{"id":"4","name":"safetyMalfunction","type":"bool"},"facets":[{"bool":[{"$":{"name":"readonly","val":"true"}}]}]},{"$":{"id":"5","name":"damperTestError","type":"bool"},"facets":[{"bool":[{"$":{"name":"readonly","val":"true"}}]}]},{"$":{"id":"6","name":"ductTemperatureHigh","type":"bool"},"facets":[{"bool":[{"$":{"name":"readonly","val":"true"}}]}]},{"$":{"id":"7","name":"smokeDetectorNotConnected","type":"bool"},"facets":[{"bool":[{"$":{"name":"readonly","val":"true"}}]}]},{"$":{"id":"8","name":"range","type":"byte"},"facets":[{"int":[{"$":{"name":"min","val":"0"}},{"$":{"name":"max","val":"1"}}],"str":[{"$":{"name":"range","val":"Nominal, Adapted"}}],"bool":[{"$":{"name":"readonly","val":"true"}}]}]},{"$":{"id":"9","name":"damperTest","type":"bool"},"facets":[{"bool":[{"$":{"name":"readonly","val":"true"}}]}]},{"$":{"id":"10","name":"tempHigher72C","type":"bool"},"facets":[{"bool":[{"$":{"name":"readonly","val":"true"}}]}]},{"$":{"id":"11","name":"internalError","type":"bool"},"facets":[{"bool":[{"$":{"name":"readonly","val":"true"}}]}]},{"$":{"id":"12","name":"damperPosition","type":"byte"},"facets":[{"int":[{"$":{"name":"min","val":"0"}},{"$":{"name":"max","val":"2"}}],"str":[{"$":{"name":"range","val":"travelling, closed, open"}}],"bool":[{"$":{"name":"readonly","val":"true"}}]}]},{"$":{"id":"13","name":"setForcedControl","type":"byte","flags":"c","default":"0"},"facets":[{"int":[{"$":{"name":"min","val":"0"}},{"$":{"name":"max","val":"9"}}],"bool":[{"$":{"name":"config","val":"true"}}],"str":[{"$":{"name":"range","val":"None, Open, Close, Max, Min, Mid, Stop, Percent100, Fast_close, Fast_open, Stop_10s"}}]}]},{"$":{"id":"14","name":"getForcedControl","type":"byte","default":"0"},"facets":[{"int":[{"$":{"name":"min","val":"0"}},{"$":{"name":"max","val":"9"}}],"str":[{"$":{"name":"range","val":"None, Open, Close, Max, Min, Mid, Stop, Percent100, Fast_close, Fast_open, Stop_10s"}}],"bool":[{"$":{"name":"readonly","val":"true"}}]}]},{"$":{"id":"15","name":"startTestRunFire","type":"byte","flags":"c","default":"1"},"facets":[{"int":[{"$":{"name":"min","val":"0"}},{"$":{"name":"max","val":"3"}}],"bool":[{"$":{"name":"config","val":"true"}}],"str":[{"$":{"name":"range","val":"Start_Adaptation, Start_Fire_Test_run, Start_Free_Damper_Test, Start_Synchronisation"}}]}]},{"$":{"id":"16","name":"fireTestRun","type":"bool"},"facets":[{"bool":[{"$":{"name":"readonly","val":"true"}}]}]},{"$":{"id":"17","name":"deviceCategory","type":"byte"},"facets":[{"int":[{"$":{"name":"min","val":"0"}},{"$":{"name":"max","val":"15"}}],"str":[{"$":{"name":"range","val":"Spare, Universal_IO, Air, Valve_linear, Valve_rotary, Window_Ventilation, Fire_Smoke, Sensor, VAV, MPL, xA, xB, xC, xD, xE, third_Party"}}],"bool":[{"$":{"name":"readonly","val":"true"}}]}]},{"$":{"id":"18","name":"builtInModule","type":"int"},"facets":[{"int":[{"$":{"name":"min","val":"0"}},{"$":{"name":"max","val":"15"}}],"str":[{"$":{"name":"range","val":"None, SR_95, Phase_Cut, Y, Temperature, LON, mA, BAE_2, LEN, Hartann, Ohm_135, CAN, EPIV, xD, xE, third_Party"}}],"bool":[{"$":{"name":"readonly","val":"true"}}]}]},{"$":{"id":"19","name":"deviceFamily","type":"short"},"facets":[{"int":[{"$":{"name":"min","val":"0"}},{"$":{"name":"max","val":"255"}}],"bool":[{"$":{"name":"readonly","val":"true"}}]}]},{"$":{"id":"20","name":"Start_Testrun_Fire","type":"void","flags":"a"}},{"$":{"id":"21","name":"Set_Forced_Control","type":"void","flags":"a"}}]},{"$":{"id":"12","name":"MpVavController","sizeof":"72","base":"sys::Component"},"facets":[{"str":[{"$":{"name":"niagaraIcon","val":"module://icons/x16/control/numericPointWr.png"}}]}],"slot":[{"$":{"id":"0","name":"address","type":"byte","flags":"c","default":"0"},"facets":[{"int":[{"$":{"name":"min","val":"0"}},{"$":{"name":"max","val":"7"}}],"bool":[{"$":{"name":"config","val":"true"}}],"str":[{"$":{"name":"range","val":"MP_1, MP_2, MP_3, MP_4, MP_5, MP_6, MP_7, MP_8"}}]}]},{"$":{"id":"1","name":"in","type":"float"},"facets":[{"float":[{"$":{"name":"min","val":"0.0"}},{"$":{"name":"max","val":"1.0"}}],"int":[{"$":{"name":"precision","val":"3"}}]}]},{"$":{"id":"2","name":"ySensorType","type":"byte","flags":"c","default":"0"},"facets":[{"int":[{"$":{"name":"min","val":"0"}},{"$":{"name":"max","val":"2"}}],"bool":[{"$":{"name":"config","val":"true"}}],"str":[{"$":{"name":"range","val":"voltage, passive850_1600, passive200_50000, switch"}}]}]},{"$":{"id":"3","name":"outVoltage","type":"float"},"facets":[{"str":[{"$":{"name":"unit","val":"volt"}}],"bool":[{"$":{"name":"readonly","val":"true"}}]}]},{"$":{"id":"4","name":"outResistance","type":"float"},"facets":[{"str":[{"$":{"name":"unit","val":"ohm"}}],"bool":[{"$":{"name":"readonly","val":"true"}}]}]},{"$":{"id":"5","name":"outSetPointFeedback","type":"float"},"facets":[{"int":[{"$":{"name":"precision","val":"3"}}],"bool":[{"$":{"name":"readonly","val":"true"}}]}]},{"$":{"id":"6","name":"outActualPos","type":"float"},"facets":[{"int":[{"$":{"name":"precision","val":"3"}}],"bool":[{"$":{"name":"readonly","val":"true"}}]}]},{"$":{"id":"7","name":"heavyUsage","type":"bool"},"facets":[{"bool":[{"$":{"name":"readonly","val":"true"}}]}]},{"$":{"id":"8","name":"controlRangeExtended","type":"bool"},"facets":[{"bool":[{"$":{"name":"readonly","val":"true"}}]}]},{"$":{"id":"9","name":"overload","type":"bool"},"facets":[{"bool":[{"$":{"name":"readonly","val":"true"}}]}]},{"$":{"id":"10","name":"setForcedControl","type":"byte","flags":"c","default":"0"},"facets":[{"int":[{"$":{"name":"min","val":"0"}},{"$":{"name":"max","val":"9"}}],"bool":[{"$":{"name":"config","val":"true"}}],"str":[{"$":{"name":"range","val":"Open, Close, Max, Min, Mid, Stop, Percent100, Fast_close, Fast_open, Stop_10s"}}]}]},{"$":{"id":"11","name":"deviceCategory","type":"byte"},"facets":[{"int":[{"$":{"name":"min","val":"0"}},{"$":{"name":"max","val":"15"}}],"str":[{"$":{"name":"range","val":"Spare, Universal_IO, Air, Valve_linear, Valve_rotary, Window_Ventilation, Fire_Smoke, Sensor, VAV, MPL, xA, xB, xC, xD, xE, third_Party"}}],"bool":[{"$":{"name":"readonly","val":"true"}}]}]},{"$":{"id":"12","name":"builtInModule","type":"int"},"facets":[{"int":[{"$":{"name":"min","val":"0"}},{"$":{"name":"max","val":"15"}}],"str":[{"$":{"name":"range","val":"None, SR_95, Phase_Cut, Y, Temperature, LON, mA, BAE_2, LEN, Hartann, Ohm_135, CAN, EPIV, xD, xE, third_Party"}}],"bool":[{"$":{"name":"readonly","val":"true"}}]}]},{"$":{"id":"13","name":"deviceFamily","type":"short"},"facets":[{"int":[{"$":{"name":"min","val":"0"}},{"$":{"name":"max","val":"255"}}],"bool":[{"$":{"name":"readonly","val":"true"}}]}]},{"$":{"id":"14","name":"Set_Forced_Control","type":"void","flags":"a"}}]},{"$":{"id":"13","name":"MplDamper","sizeof":"56","base":"sys::Component"},"facets":[{"str":[{"$":{"name":"niagaraIcon","val":"module://icons/x16/control/numericPointWr.png"}}]}],"slot":[{"$":{"id":"0","name":"address","type":"byte","flags":"c","default":"0"},"facets":[{"int":[{"$":{"name":"min","val":"0"}},{"$":{"name":"max","val":"7"}}],"bool":[{"$":{"name":"config","val":"true"}}],"str":[{"$":{"name":"range","val":"MP_1, MP_2, MP_3, MP_4, MP_5, MP_6, MP_7, MP_8"}}]}]},{"$":{"id":"1","name":"in","type":"float"},"facets":[{"float":[{"$":{"name":"min","val":"0.0"}},{"$":{"name":"max","val":"1.0"}}],"int":[{"$":{"name":"precision","val":"3"}}]}]},{"$":{"id":"2","name":"outSetPointFeedback","type":"float"},"facets":[{"int":[{"$":{"name":"precision","val":"3"}}],"bool":[{"$":{"name":"readonly","val":"true"}}]}]},{"$":{"id":"3","name":"outActualPos","type":"float"},"facets":[{"int":[{"$":{"name":"precision","val":"3"}}],"bool":[{"$":{"name":"readonly","val":"true"}}]}]},{"$":{"id":"4","name":"deviceCategory","type":"byte"},"facets":[{"int":[{"$":{"name":"min","val":"0"}},{"$":{"name":"max","val":"15"}}],"str":[{"$":{"name":"range","val":"Spare, Universal_IO, Air, Valve_linear, Valve_rotary, Window_Ventilation, Fire_Smoke, Sensor, VAV, MPL, xA, xB, xC, xD, xE, third_Party"}}],"bool":[{"$":{"name":"readonly","val":"true"}}]}]},{"$":{"id":"5","name":"builtInModule","type":"int"},"facets":[{"int":[{"$":{"name":"min","val":"0"}},{"$":{"name":"max","val":"15"}}],"str":[{"$":{"name":"range","val":"None, SR_95, Phase_Cut, Y, Temperature, LON, mA, BAE_2, LEN, Hartann, Ohm_135, CAN, EPIV, xD, xE, third_Party"}}],"bool":[{"$":{"name":"readonly","val":"true"}}]}]},{"$":{"id":"6","name":"deviceFamily","type":"short"},"facets":[{"int":[{"$":{"name":"min","val":"0"}},{"$":{"name":"max","val":"255"}}],"bool":[{"$":{"name":"readonly","val":"true"}}]}]}]},{"$":{"id":"14","name":"MpxController","sizeof":"72","base":"sys::Component"},"facets":[{"str":[{"$":{"name":"niagaraIcon","val":"module://icons/x16/control/numericPointWr.png"}}]}],"slot":[{"$":{"id":"0","name":"address","type":"byte","flags":"c","default":"0"},"facets":[{"int":[{"$":{"name":"min","val":"0"}},{"$":{"name":"max","val":"7"}}],"bool":[{"$":{"name":"config","val":"true"}}],"str":[{"$":{"name":"range","val":"MP_1, MP_2, MP_3, MP_4, MP_5, MP_6, MP_7, MP_8"}}]}]},{"$":{"id":"1","name":"in","type":"float"},"facets":[{"float":[{"$":{"name":"min","val":"0.0"}},{"$":{"name":"max","val":"1.0"}}],"int":[{"$":{"name":"precision","val":"3"}}]}]},{"$":{"id":"2","name":"ySensorType1","type":"byte","flags":"c","default":"0"},"facets":[{"int":[{"$":{"name":"min","val":"0"}},{"$":{"name":"max","val":"3"}}],"bool":[{"$":{"name":"config","val":"true"}}],"str":[{"$":{"name":"range","val":"Resistance, Voltage, Switch"}}]}]},{"$":{"id":"3","name":"outResistance1","type":"float"},"facets":[{"str":[{"$":{"name":"unit","val":"ohm"}}],"bool":[{"$":{"name":"readonly","val":"true"}}]}]},{"$":{"id":"4","name":"outVoltage1","type":"float"},"facets":[{"str":[{"$":{"name":"unit","val":"volt"}}],"bool":[{"$":{"name":"readonly","val":"true"}}]}]},{"$":{"id":"5","name":"switch1","type":"bool"},"facets":[{"bool":[{"$":{"name":"readonly","val":"true"}}]}]},{"$":{"id":"6","name":"ySensorType2","type":"byte","flags":"c","default":"0"},"facets":[{"int":[{"$":{"name":"min","val":"0"}},{"$":{"name":"max","val":"3"}}],"bool":[{"$":{"name":"config","val":"true"}}],"str":[{"$":{"name":"range","val":"Resistance, Voltage, Switch"}}]}]},{"$":{"id":"7","name":"outResistance2","type":"float"},"facets":[{"str":[{"$":{"name":"unit","val":"ohm"}}],"bool":[{"$":{"name":"readonly","val":"true"}}]}]},{"$":{"id":"8","name":"outVoltage2","type":"float"},"facets":[{"str":[{"$":{"name":"unit","val":"volt"}}],"bool":[{"$":{"name":"readonly","val":"true"}}]}]},{"$":{"id":"9","name":"switch2","type":"bool"},"facets":[{"bool":[{"$":{"name":"readonly","val":"true"}}]}]},{"$":{"id":"10","name":"outSetPointFeedback","type":"float"},"facets":[{"int":[{"$":{"name":"precision","val":"3"}}],"bool":[{"$":{"name":"readonly","val":"true"}}]}]},{"$":{"id":"11","name":"outActualPos","type":"float"},"facets":[{"int":[{"$":{"name":"precision","val":"3"}}],"bool":[{"$":{"name":"readonly","val":"true"}}]}]}]},{"$":{"id":"15","name":"NvMemGetBool","sizeof":"48","base":"sys::Component"},"facets":[{"str":[{"$":{"name":"niagaraIcon","val":"module://icons/x16/control/booleanPoint.png"}}]}],"slot":[{"$":{"id":"0","name":"address","type":"int","flags":"c","default":"0"},"facets":[{"int":[{"$":{"name":"min","val":"0"}},{"$":{"name":"max","val":"23"}}],"bool":[{"$":{"name":"config","val":"true"}}]}]},{"$":{"id":"1","name":"bitPos","type":"int","flags":"c","default":"0"},"facets":[{"int":[{"$":{"name":"min","val":"0"}},{"$":{"name":"max","val":"31"}}],"bool":[{"$":{"name":"config","val":"true"}}]}]},{"$":{"id":"2","name":"out","type":"bool"},"facets":[{"bool":[{"$":{"name":"readonly","val":"true"}}]}]}]},{"$":{"id":"16","name":"NvMemGetEnum","sizeof":"44","base":"sys::Component"},"facets":[{"str":[{"$":{"name":"niagaraIcon","val":"module://icons/x16/control/enumPoint.png"}}]}],"slot":[{"$":{"id":"0","name":"address","type":"int","flags":"c","default":"0"},"facets":[{"int":[{"$":{"name":"min","val":"0"}},{"$":{"name":"max","val":"23"}}],"bool":[{"$":{"name":"config","val":"true"}}]}]},{"$":{"id":"1","name":"out","type":"int","default":"0"},"facets":[{"bool":[{"$":{"name":"readonly","val":"true"}}]}]}]},{"$":{"id":"17","name":"NvMemGetFloat","sizeof":"44","base":"sys::Component"},"facets":[{"str":[{"$":{"name":"niagaraIcon","val":"module://icons/x16/control/numericPoint.png"}}]}],"slot":[{"$":{"id":"0","name":"address","type":"int","flags":"c","default":"0"},"facets":[{"int":[{"$":{"name":"min","val":"0"}},{"$":{"name":"max","val":"23"}}],"bool":[{"$":{"name":"config","val":"true"}}]}]},{"$":{"id":"1","name":"out","type":"float"},"facets":[{"bool":[{"$":{"name":"readonly","val":"true"}}]}]}]},{"$":{"id":"18","name":"NvMemSetBool","sizeof":"48","base":"sys::Component"},"facets":[{"str":[{"$":{"name":"niagaraIcon","val":"module://icons/x16/control/booleanPointWr.png"}}]}],"slot":[{"$":{"id":"0","name":"address","type":"int","flags":"c","default":"0"},"facets":[{"int":[{"$":{"name":"min","val":"0"}},{"$":{"name":"max","val":"23"}}],"bool":[{"$":{"name":"config","val":"true"}}]}]},{"$":{"id":"1","name":"bitPos","type":"int","flags":"c","default":"0"},"facets":[{"int":[{"$":{"name":"min","val":"0"}},{"$":{"name":"max","val":"31"}}],"bool":[{"$":{"name":"config","val":"true"}}]}]},{"$":{"id":"2","name":"in","type":"bool"}},{"$":{"id":"3","name":"set","type":"bool","default":"false"}}]},{"$":{"id":"19","name":"NvMemSetEnum","sizeof":"48","base":"sys::Component"},"facets":[{"str":[{"$":{"name":"niagaraIcon","val":"module://icons/x16/control/enumPointWr.png"}}]}],"slot":[{"$":{"id":"0","name":"address","type":"int","flags":"c","default":"0"},"facets":[{"int":[{"$":{"name":"min","val":"0"}},{"$":{"name":"max","val":"23"}}],"bool":[{"$":{"name":"config","val":"true"}}]}]},{"$":{"id":"1","name":"in","type":"int"}},{"$":{"id":"2","name":"set","type":"bool","default":"false"}}]},{"$":{"id":"20","name":"NvMemSetFloat","sizeof":"48","base":"sys::Component"},"facets":[{"str":[{"$":{"name":"niagaraIcon","val":"module://icons/x16/control/numericPointWr.png"}}]}],"slot":[{"$":{"id":"0","name":"address","type":"int","flags":"c","default":"0"},"facets":[{"int":[{"$":{"name":"min","val":"0"}},{"$":{"name":"max","val":"23"}}],"bool":[{"$":{"name":"config","val":"true"}}]}]},{"$":{"id":"1","name":"in","type":"float"}},{"$":{"id":"2","name":"set","type":"bool","default":"false"}}]},{"$":{"id":"21","name":"SccPlatformService","sizeof":"620","base":"sys::PlatformService"},"slot":[{"$":{"id":"0","name":"systemLoad","type":"float","default":"0.0"},"facets":[{"str":[{"$":{"name":"unit","val":"percent"}}],"bool":[{"$":{"name":"readonly","val":"true"}}]}]},{"$":{"id":"1","name":"ipAddress","type":"sys::Buf","flags":"s"},"facets":[{"bool":[{"$":{"name":"asStr","val":"true"}},{"$":{"name":"summary","val":"false"}}],"int":[{"$":{"name":"max","val":"16"}}]}]},{"$":{"id":"2","name":"ipNetMask","type":"sys::Buf","flags":"s"},"facets":[{"bool":[{"$":{"name":"asStr","val":"true"}},{"$":{"name":"summary","val":"false"}}],"int":[{"$":{"name":"max","val":"16"}}]}]},{"$":{"id":"3","name":"ipGateway","type":"sys::Buf","flags":"s"},"facets":[{"bool":[{"$":{"name":"asStr","val":"true"}},{"$":{"name":"summary","val":"false"}}],"int":[{"$":{"name":"max","val":"16"}}]}]},{"$":{"id":"4","name":"ipDns1","type":"sys::Buf","flags":"s"},"facets":[{"bool":[{"$":{"name":"asStr","val":"true"}},{"$":{"name":"summary","val":"false"}}],"int":[{"$":{"name":"max","val":"16"}}]}]},{"$":{"id":"5","name":"ipDns2","type":"sys::Buf","flags":"s"},"facets":[{"bool":[{"$":{"name":"asStr","val":"true"}},{"$":{"name":"summary","val":"false"}}],"int":[{"$":{"name":"max","val":"16"}}]}]},{"$":{"id":"6","name":"ipDns3","type":"sys::Buf","flags":"s"},"facets":[{"bool":[{"$":{"name":"asStr","val":"true"}},{"$":{"name":"summary","val":"false"}}],"int":[{"$":{"name":"max","val":"16"}}]}]},{"$":{"id":"7","name":"sntpAddress","type":"sys::Buf","flags":"s"},"facets":[{"bool":[{"$":{"name":"asStr","val":"true"}},{"$":{"name":"summary","val":"false"}}],"int":[{"$":{"name":"max","val":"256"}}]}]},{"$":{"id":"8","name":"modbusPort","type":"int"},"facets":[{"int":[{"$":{"name":"min","val":"0"}},{"$":{"name":"max","val":"65535"}}],"bool":[{"$":{"name":"summary","val":"false"}}]}]},{"$":{"id":"9","name":"modbusUnitId","type":"int"},"facets":[{"int":[{"$":{"name":"min","val":"0"}},{"$":{"name":"max","val":"255"}}],"bool":[{"$":{"name":"summary","val":"false"}}]}]},{"$":{"id":"10","name":"modbusRtuEnabled","type":"bool","flags":"c","default":"false"},"facets":[{"bool":[{"$":{"name":"config","val":"true"}},{"$":{"name":"allowNull","val":"false"}}],"str":[{"$":{"name":"falseText","val":"disabled"}},{"$":{"name":"trueText","val":"enabled"}}]}]},{"$":{"id":"11","name":"modbusRtuBaud","type":"int","flags":"c","default":"5"},"facets":[{"int":[{"$":{"name":"min","val":"0"}},{"$":{"name":"max","val":"10"}}],"bool":[{"$":{"name":"config","val":"true"}}],"str":[{"$":{"name":"range","val":"baud_1200, baud_2400, baud_4800, baud_9600, baud_14400, baud_19200, baud_28800, baud_38400, baud_57600, baud_76800, baud_115200"}}]}]},{"$":{"id":"12","name":"modbusRtuParity","type":"int","flags":"c","default":"0"},"facets":[{"int":[{"$":{"name":"min","val":"0"}},{"$":{"name":"max","val":"2"}}],"bool":[{"$":{"name":"config","val":"true"}}],"str":[{"$":{"name":"range","val":"none, odd, even"}}]}]},{"$":{"id":"13","name":"modbusRtuStopBits","type":"int","flags":"c","default":"1"},"facets":[{"int":[{"$":{"name":"min","val":"1"}},{"$":{"name":"max","val":"2"}}],"bool":[{"$":{"name":"config","val":"true"}}]}]},{"$":{"id":"14","name":"restart","type":"void","flags":"a"},"facets":[{"bool":[{"$":{"name":"confirmRequired","val":"true"}}]}]},{"$":{"id":"15","name":"reboot","type":"void","flags":"a"},"facets":[{"bool":[{"$":{"name":"confirmRequired","val":"true"}}]}]}]}]}}