{"kitManifest":{"$":{"name":"SysMikIcsManualCtrl","checksum":"1bcf7e2a","hasNatives":"false","doc":"false","version":"1.2.28","vendor":"SysMik","description":"ICS Manual Control","buildHost":"GS-W7-7-002","buildTime":"2014-06-11T16:03:54.592+02:00"},"depends":[{"depend":[{"$":{"on":"sys 1.2"}},{"$":{"on":"SysMikNativeLib 1.2"}}]}],"type":[{"$":{"id":"0","name":"DisplayDec","sizeof":"44","base":"sys::Component"},"facets":[{"str":[{"$":{"name":"niagaraIcon","val":"module://icons/x16/lcd.png"}}]}],"slot":[{"$":{"id":"0","name":"precision","type":"int","flags":"c","default":"0"},"facets":[{"int":[{"$":{"name":"min","val":"0"}},{"$":{"name":"max","val":"2"}}],"bool":[{"$":{"name":"config","val":"true"}}]}]},{"$":{"id":"1","name":"in","type":"float"}}]},{"$":{"id":"1","name":"DisplayHex","sizeof":"40","base":"sys::Component"},"facets":[{"str":[{"$":{"name":"niagaraIcon","val":"module://icons/x16/lcd.png"}}]}],"slot":[{"$":{"id":"0","name":"in","type":"int","default":"0"},"facets":[{"int":[{"$":{"name":"min","val":"0"}},{"$":{"name":"max","val":"4095"}},{"$":{"name":"radix","val":"16"}}]}]}]},{"$":{"id":"2","name":"DisplayRaw","sizeof":"48","base":"sys::Component"},"facets":[{"str":[{"$":{"name":"niagaraIcon","val":"module://icons/x16/lcd.png"}}]}],"slot":[{"$":{"id":"0","name":"inLeft","type":"int","default":"0"},"facets":[{"int":[{"$":{"name":"min","val":"0"}},{"$":{"name":"max","val":"255"}}]}]},{"$":{"id":"1","name":"inMiddle","type":"int","default":"0"},"facets":[{"int":[{"$":{"name":"min","val":"0"}},{"$":{"name":"max","val":"255"}}]}]},{"$":{"id":"2","name":"inRight","type":"int","default":"0"},"facets":[{"int":[{"$":{"name":"min","val":"0"}},{"$":{"name":"max","val":"255"}}]}]}]},{"$":{"id":"3","name":"Led","sizeof":"40","base":"sys::Component"},"facets":[{"str":[{"$":{"name":"niagaraIcon","val":"module://icons/x16/control/booleanPointWr.png"}}]}],"slot":[{"$":{"id":"0","name":"channel","type":"byte","flags":"c","default":"0"},"facets":[{"int":[{"$":{"name":"min","val":"0"}},{"$":{"name":"max","val":"5"}}],"bool":[{"$":{"name":"config","val":"true"}}],"str":[{"$":{"name":"range","val":"A_red, A_green, B_red, B_green, Test_red, Test_green"}}]}]},{"$":{"id":"1","name":"in","type":"bool"}}]},{"$":{"id":"4","name":"Leds","sizeof":"44","base":"sys::Component"},"facets":[{"str":[{"$":{"name":"niagaraIcon","val":"module://icons/x16/control/booleanPointWr.png"}}]}],"slot":[{"$":{"id":"0","name":"colorA","type":"byte","flags":"c","default":"0"},"facets":[{"int":[{"$":{"name":"min","val":"0"}},{"$":{"name":"max","val":"2"}}],"bool":[{"$":{"name":"config","val":"true"}}],"str":[{"$":{"name":"range","val":"Red, Orange, Green"}}]}]},{"$":{"id":"1","name":"inA","type":"bool","default":"false"}},{"$":{"id":"2","name":"colorB","type":"byte","flags":"c","default":"0"},"facets":[{"int":[{"$":{"name":"min","val":"0"}},{"$":{"name":"max","val":"2"}}],"bool":[{"$":{"name":"config","val":"true"}}],"str":[{"$":{"name":"range","val":"Red, Orange, Green"}}]}]},{"$":{"id":"3","name":"inB","type":"bool","default":"false"}},{"$":{"id":"4","name":"colorTest","type":"byte","flags":"c","default":"0"},"facets":[{"int":[{"$":{"name":"min","val":"0"}},{"$":{"name":"max","val":"2"}}],"bool":[{"$":{"name":"config","val":"true"}}],"str":[{"$":{"name":"range","val":"Red, Orange, Green"}}]}]},{"$":{"id":"5","name":"inTest","type":"bool","default":"false"}}]},{"$":{"id":"5","name":"PushButton","sizeof":"40","base":"sys::Component"},"facets":[{"str":[{"$":{"name":"niagaraIcon","val":"module://icons/x16/control/booleanPoint.png"}}]}],"slot":[{"$":{"id":"0","name":"channel","type":"byte","flags":"c","default":"0"},"facets":[{"int":[{"$":{"name":"min","val":"0"}},{"$":{"name":"max","val":"10"}}],"bool":[{"$":{"name":"config","val":"true"}}],"str":[{"$":{"name":"range","val":"PB_1, PB_2, PB_3, PB_4, PB_5, PB_6, PB_7, PB_8, PB_Test, PB_Left, PB_Right"}}]}]},{"$":{"id":"1","name":"out","type":"bool"},"facets":[{"bool":[{"$":{"name":"readonly","val":"true"}}]}]}]},{"$":{"id":"6","name":"Test","sizeof":"40","base":"sys::Component"},"facets":[{"str":[{"$":{"name":"niagaraIcon","val":"module://icons/x16/pan.png"}}]}],"slot":[{"$":{"id":"0","name":"testButton","type":"bool","default":"true"},"facets":[{"str":[{"$":{"name":"falseText","val":"disabled"}},{"$":{"name":"trueText","val":"enabled"}}],"bool":[{"$":{"name":"allowNull","val":"false"}}]}]},{"$":{"id":"1","name":"testMode","type":"bool","default":"false"},"facets":[{"str":[{"$":{"name":"falseText","val":"deactive"}},{"$":{"name":"trueText0","val":"active"}}],"bool":[{"$":{"name":"readonly","val":"true"}}]}]},{"$":{"id":"2","name":"Activate","type":"void","flags":"a"}},{"$":{"id":"3","name":"Deactivate","type":"void","flags":"a"}}]}]}}